graphinf/__init__.py
graphinf/_graphinf.cpython-310-x86_64-linux-gnu.so
graphinf/data/__init__.py
graphinf/data/dynamics.py
graphinf/data/uncertain.py
graphinf/data/util.py
graphinf/data/wrapper.py
graphinf/graph/__init__.py
graphinf/graph/degree_sequences.py
graphinf/graph/util.py
graphinf/graph/wrapper.py
graphinf/metadata.py
graphinf/utility.py
graphinf/wrapper.py
graphinf-0.3.1.dist-info/METADATA
graphinf-0.3.1.dist-info/WHEEL
graphinf-0.3.1.dist-info/entry_points.txt
graphinf-0.3.1.dist-info/licenses/LICENSE
graphinf-0.3.1.dist-info/RECORD
