Metadata-Version: 2.1
Name: graphinf
Version: 0.3.1
Summary: A Markov chain Monte-Carlo for graph inference.
Author: Charles Murphy
Classifier: Development Status :: 4 - Beta
Classifier: License :: OSI Approved :: GNU General Public License v3 or later (GPLv3+)
Classifier: Programming Language :: Python :: 3 :: Only
Requires-Python: >=3.7
License-File: LICENSE
